{
    "melee_weapons": [
        {"name": "Combat Knife", "PEN": 5},
        {"name": "Machete", "PEN": 9},
        {"name": "Karambit", "PEN": 7},
        {"name": "Fairbairn-Sykes Dagger", "PEN": 7},
        {"name": "Tactical Tomahawk", "PEN": 11},
        {"name": "Push Dagger", "PEN": 6},
        {"name": "Bayonet", "PEN": 10},
        {"name": "Trench Knife", "PEN": 7},
        {"name": "Bowie Knife", "PEN": 9},
        {"name": "Trench Club", "PEN": 12},
        {"name": "Expandable Baton", "PEN": 8},
        {"name": "Knuckle Duster", "PEN": 6},
        {"name": "Warhammer", "PEN": 14},
        {"name": "Halberd", "PEN": 16},
        {"name": "Poleaxe", "PEN": 15},
        {"name": "Glaive", "PEN": 13},
        {"name": "Battle Axe", "PEN": 15},
        {"name": "Dane Axe", "PEN": 17},
        {"name": "Flail", "PEN": 14},
        {"name": "Morning Star", "PEN": 16},
        {"name": "Mace", "PEN": 14},
        {"name": "Katana", "PEN": 10},
        {"name": "Rapier", "PEN": 7},
        {"name": "Longsword", "PEN": 12},
        {"name": "Greatsword", "PEN": 17},
        {"name": "Bec de Corbin", "PEN": 18},
        {"name": "Pike", "PEN": 11},
        {"name": "Lance", "PEN": 20},
        {"name": "Tetsubo", "PEN": 18},
        {"name": "Naginata", "PEN": 13},
        {"name": "Kukri", "PEN": 9},
        {"name": "Vibroblade", "PEN": 20},
        {"name": "Energy Blade", "PEN": 30},
        {"name": "Power Fist", "PEN": 22},
        {"name": "Monomolecular Knife", "PEN": 25}
    ]
}

